ReqGuard/__init__.py
ReqGuard/__version__.py
ReqGuard/_internal_utils.py
ReqGuard/adapters.py
ReqGuard/api.py
ReqGuard/auth.py
ReqGuard/certs.py
ReqGuard/compat.py
ReqGuard/cookies.py
ReqGuard/exceptions.py
ReqGuard/help.py
ReqGuard/hooks.py
ReqGuard/models.py
ReqGuard/packages.py
ReqGuard/security.py
ReqGuard/sessions.py
ReqGuard/status_codes.py
ReqGuard/structures.py
ReqGuard/utils.py
reqguard-1.2.0.dist-info/licenses/LICENSE
reqguard-1.2.0.dist-info/licenses/NOTICE
reqguard-1.2.0.dist-info/METADATA
reqguard-1.2.0.dist-info/WHEEL
reqguard-1.2.0.dist-info/top_level.txt
reqguard-1.2.0.dist-info/RECORD
