Metadata-Version: 2.4
Name: ReqGuard
Version: 1.2.0
Summary: Python HTTP Security Library
Home-page: https://github.com/x6-u/ReqGuard
Author: mero
Author-email: mero <merops@gmail.com>
Maintainer-email: mero <merops@gmail.com>
License: Apache-2.0
Project-URL: Homepage, https://github.com/x6-u/ReqGuard
Project-URL: Documentation, https://github.com/x6-u/ReqGuard
Project-URL: Repository, https://github.com/x6-u/ReqGuard
Project-URL: Telegram, https://t.me/QP4RM
Project-URL: Changelog, https://github.com/x6-u/ReqGuard/blob/main/CHANGELOG.md
Keywords: http,https,security,ssrf,protection,rate-limiting,dns-rebinding,threat-detection,web-security,api-security
Classifier: Development Status :: 5 - Production/Stable
Classifier: Environment :: Web Environment
Classifier: Intended Audience :: Developers
Classifier: License :: OSI Approved :: Apache Software License
Classifier: Natural Language :: English
Classifier: Operating System :: OS Independent
Classifier: Programming Language :: Python
Classifier: Programming Language :: Python :: 3
Classifier: Programming Language :: Python :: 3.6
Classifier: Programming Language :: Python :: 3.7
Classifier: Programming Language :: Python :: 3.8
Classifier: Programming Language :: Python :: 3.9
Classifier: Programming Language :: Python :: 3.10
Classifier: Programming Language :: Python :: 3.11
Classifier: Programming Language :: Python :: 3.12
Classifier: Programming Language :: Python :: 3.13
Classifier: Programming Language :: Python :: 3.14
Classifier: Programming Language :: Python :: 3 :: Only
Classifier: Programming Language :: Python :: Implementation :: CPython
Classifier: Programming Language :: Python :: Implementation :: PyPy
Classifier: Topic :: Internet :: WWW/HTTP
Classifier: Topic :: Software Development :: Libraries
Classifier: Topic :: Security
Requires-Python: >=3.6
License-File: LICENSE
License-File: NOTICE
Requires-Dist: urllib3<3,>=1.21.1
Requires-Dist: certifi>=2017.4.17
Requires-Dist: charset-normalizer<4,>=2
Requires-Dist: idna<4,>=2.5
Provides-Extra: http2
Requires-Dist: httpx>=0.23.0; extra == "http2"
Requires-Dist: h2>=4.0.0; extra == "http2"
Provides-Extra: http3
Requires-Dist: aioquic>=0.9.0; extra == "http3"
Provides-Extra: security
Requires-Dist: cryptography>=2.5; extra == "security"
Provides-Extra: socks
Requires-Dist: PySocks!=1.5.7,>=1.5.6; extra == "socks"
Provides-Extra: all
Requires-Dist: httpx>=0.23.0; extra == "all"
Requires-Dist: h2>=4.0.0; extra == "all"
Requires-Dist: aioquic>=0.9.0; extra == "all"
Requires-Dist: cryptography>=2.5; extra == "all"
Requires-Dist: PySocks!=1.5.7,>=1.5.6; extra == "all"
Dynamic: author
Dynamic: home-page
Dynamic: license-file
Dynamic: requires-python
